liveprofiler/__init__.py
liveprofiler/app.py
liveprofiler/collector.py
liveprofiler/model.py
liveprofiler/visualizer.py
liveprofiler/wsgi.py
liveprofiler/static/d3.flameGraph.css
liveprofiler/static/d3.flameGraph.js
liveprofiler/static/d3.js
liveprofiler/static/d3.slider.css
liveprofiler/static/d3.slider.js
liveprofiler/static/d3.tip.v0.6.3.js
liveprofiler/templates/graph.html
liveprofiler/templates/index.html
liveprofiler-1.0.0.dist-info/DESCRIPTION.rst
liveprofiler-1.0.0.dist-info/METADATA
liveprofiler-1.0.0.dist-info/RECORD
liveprofiler-1.0.0.dist-info/WHEEL
liveprofiler-1.0.0.dist-info/metadata.json
liveprofiler-1.0.0.dist-info/top_level.txt
