Metadata-Version: 2.0
Name: liveprofiler
Version: 1.0.0
Summary: Package for profiling WSGI applications on production
Home-page: https://github.com/fieldaware/liveprofiler
Author: Piotr Szymanski
Author-email: piotr.szymanski@fieldaware.com
License: MIT
Platform: UNKNOWN
Requires-Dist: click (==6.6)
Requires-Dist: dateparser (==0.3.5)
Requires-Dist: flask (>=0.10.1)
Requires-Dist: liveprofiler-sampler (==0.9.2)
Requires-Dist: requests (>=2.4.3)
Requires-Dist: uWSGI (==2.0.13.1)
